MANIFEST.in
setup.py
email_reply_parser/__init__.py
email_reply_parser/version.py
email_reply_parser.egg-info/PKG-INFO
email_reply_parser.egg-info/SOURCES.txt
email_reply_parser.egg-info/dependency_links.txt
email_reply_parser.egg-info/top_level.txt
test/test_email_reply_parser.py