Metadata-Version: 1.0
Name: email-reply-parser
Version: 0.2.0
Summary: Email reply parser
Home-page: https://github.com/zapier/email-reply-parser
Author: Royce Haynes
Author-email: royce.haynes@gmail.com
License: MIT
Platform: UNKNOWN
